{
  "annotations": {
    "list": [
      {
        "builtIn": 1,
        "datasource": "-- Grafana --",
        "enable": true,
        "hide": true,
        "iconColor": "rgba(0, 211, 255, 1)",
        "name": "Annotations & Alerts",
        "type": "dashboard"
      }
    ]
  },
  "editable": true,
  "gnetId": null,
  "graphTooltip": 0,
  "id": 1,
  "links": [],
  "panels": [
    {
      "datasource": null,
      "description": "",
      "fieldConfig": {
        "defaults": {
          "color": {
            "mode": "palette-classic"
          },
          "custom": {
            "axisLabel": "",
            "axisPlacement": "auto",
            "barAlignment": 0,
            "drawStyle": "line",
            "fillOpacity": 10,
            "gradientMode": "none",
            "hideFrom": {
              "graph": false,
              "legend": false,
              "tooltip": false
            },
            "lineInterpolation": "linear",
            "lineWidth": 1,
            "pointSize": 5,
            "scaleDistribution": {
              "type": "linear"
            },
            "showPoints": "never",
            "spanNulls": true
          },
          "mappings": [],
          "thresholds": {
            "mode": "percentage",
            "steps": [
              {
                "color": "green",
                "value": null
              }
            ]
          },
          "unit": "percent"
        },
        "overrides": [
          {
            "matcher": {
              "id": "byName",
              "options": "percentage"
            },
            "properties": [
              {
                "id": "color",
                "value": {
                  "fixedColor": "blue",
                  "mode": "fixed"
                }
              }
            ]
          }
        ]
      },
      "gridPos": {
        "h": 9,
        "w": 12,
        "x": 0,
        "y": 0
      },
      "id": 2,
      "options": {
        "graph": {},
        "legend": {
          "calcs": [],
          "displayMode": "list",
          "placement": "bottom"
        },
        "tooltipOptions": {
          "mode": "single"
        }
      },
      "pluginVersion": "7.5.7",
      "targets": [
        {
          "format": "time_series",
          "group": [],
          "metricColumn": "none",
          "rawQuery": true,
          "rawSql": "SELECT\n  UNIX_TIMESTAMP(timestamp) AS \"time\",\n  percentage\nFROM humidity\nWHERE\n  $__timeFilter(timestamp)\nORDER BY timestamp",
          "refId": "A",
          "select": [
            [
              {
                "params": [
                  "percentage"
                ],
                "type": "column"
              }
            ]
          ],
          "table": "humidity",
          "timeColumn": "timestamp",
          "timeColumnType": "timestamp",
          "where": [
            {
              "name": "$__timeFilter",
              "params": [],
              "type": "macro"
            }
          ]
        }
      ],
      "timeFrom": null,
      "timeShift": null,
      "title": "Humidity",
      "type": "timeseries"
    },
    {
      "datasource": null,
      "description": "",
      "fieldConfig": {
        "defaults": {
          "color": {
            "mode": "palette-classic"
          },
          "custom": {
            "axisLabel": "",
            "axisPlacement": "auto",
            "barAlignment": 0,
            "drawStyle": "line",
            "fillOpacity": 10,
            "gradientMode": "none",
            "hideFrom": {
              "graph": false,
              "legend": false,
              "tooltip": false
            },
            "lineInterpolation": "linear",
            "lineWidth": 1,
            "pointSize": 5,
            "scaleDistribution": {
              "type": "linear"
            },
            "showPoints": "never",
            "spanNulls": true
          },
          "mappings": [],
          "thresholds": {
            "mode": "absolute",
            "steps": [
              {
                "color": "green",
                "value": null
              },
              {
                "color": "red",
                "value": 80
              }
            ]
          },
          "unit": "celsius"
        },
        "overrides": [
          {
            "matcher": {
              "id": "byName",
              "options": "degrees"
            },
            "properties": [
              {
                "id": "color",
                "value": {
                  "fixedColor": "red",
                  "mode": "fixed"
                }
              }
            ]
          }
        ]
      },
      "gridPos": {
        "h": 8,
        "w": 12,
        "x": 12,
        "y": 0
      },
      "id": 123127,
      "interval": "3s",
      "options": {
        "graph": {},
        "legend": {
          "calcs": [],
          "displayMode": "list",
          "placement": "bottom"
        },
        "tooltipOptions": {
          "mode": "single"
        }
      },
      "pluginVersion": "7.5.7",
      "targets": [
        {
          "format": "time_series",
          "group": [],
          "metricColumn": "none",
          "rawQuery": true,
          "rawSql": "SELECT\n   UNIX_TIMESTAMP(timestamp) AS \"time\",\n  degrees\nFROM temperature\nORDER BY timestamp",
          "refId": "A",
          "select": [
            [
              {
                "params": [
                  "degrees"
                ],
                "type": "column"
              }
            ]
          ],
          "table": "temperature",
          "timeColumn": "timestamp",
          "timeColumnType": "timestamp",
          "where": []
        }
      ],
      "timeFrom": null,
      "timeShift": null,
      "title": "Temperature",
      "type": "timeseries"
    },
    {
      "datasource": null,
      "description": "",
      "fieldConfig": {
        "defaults": {
          "color": {
            "mode": "thresholds"
          },
          "mappings": [],
          "thresholds": {
            "mode": "absolute",
            "steps": [
              {
                "color": "green",
                "value": null
              },
              {
                "color": "red",
                "value": 80
              }
            ]
          },
          "unit": "short"
        },
        "overrides": [
          {
            "matcher": {
              "id": "byName",
              "options": "quantity"
            },
            "properties": [
              {
                "id": "color",
                "value": {
                  "fixedColor": "orange",
                  "mode": "fixed"
                }
              }
            ]
          }
        ]
      },
      "gridPos": {
        "h": 8,
        "w": 12,
        "x": 12,
        "y": 8
      },
      "id": 4,
      "options": {
        "colorMode": "value",
        "graphMode": "area",
        "justifyMode": "auto",
        "orientation": "auto",
        "reduceOptions": {
          "calcs": [
            "lastNotNull"
          ],
          "fields": "",
          "values": false
        },
        "text": {},
        "textMode": "auto"
      },
      "pluginVersion": "7.5.7",
      "targets": [
        {
          "format": "time_series",
          "group": [],
          "metricColumn": "none",
          "rawQuery": true,
          "rawSql": "SELECT\n  UNIX_TIMESTAMP(timestamp) AS \"time\",\n  quantity\nFROM presence\nWHERE\n  $__timeFilter(timestamp)\nORDER BY timestamp",
          "refId": "A",
          "select": [
            [
              {
                "params": [
                  "quantity"
                ],
                "type": "column"
              }
            ]
          ],
          "table": "presence",
          "timeColumn": "timestamp",
          "timeColumnType": "timestamp",
          "where": [
            {
              "name": "$__timeFilter",
              "params": [],
              "type": "macro"
            }
          ]
        }
      ],
      "timeFrom": null,
      "timeShift": null,
      "title": "Presence",
      "type": "stat"
    },
    {
      "datasource": null,
      "fieldConfig": {
        "defaults": {
          "color": {
            "mode": "palette-classic"
          },
          "custom": {
            "axisLabel": "",
            "axisPlacement": "auto",
            "barAlignment": 0,
            "drawStyle": "line",
            "fillOpacity": 10,
            "gradientMode": "none",
            "hideFrom": {
              "graph": false,
              "legend": false,
              "tooltip": false
            },
            "lineInterpolation": "linear",
            "lineWidth": 1,
            "pointSize": 5,
            "scaleDistribution": {
              "type": "linear"
            },
            "showPoints": "never",
            "spanNulls": true
          },
          "mappings": [],
          "thresholds": {
            "mode": "absolute",
            "steps": [
              {
                "color": "green",
                "value": null
              },
              {
                "color": "red",
                "value": 80
              }
            ]
          },
          "unit": "ppm"
        },
        "overrides": []
      },
      "gridPos": {
        "h": 8,
        "w": 12,
        "x": 0,
        "y": 9
      },
      "id": 123125,
      "options": {
        "graph": {},
        "legend": {
          "calcs": [],
          "displayMode": "list",
          "placement": "bottom"
        },
        "tooltipOptions": {
          "mode": "single"
        }
      },
      "pluginVersion": "7.5.7",
      "targets": [
        {
          "format": "time_series",
          "group": [],
          "metricColumn": "none",
          "rawQuery": true,
          "rawSql": "SELECT\n  UNIX_TIMESTAMP(timestamp) AS \"time\",\n  concentration\nFROM air_quality\nWHERE\n  $__timeFilter(timestamp) \n  AND node = 2\nORDER BY timestamp",
          "refId": "A",
          "select": [
            [
              {
                "params": [
                  "concentration"
                ],
                "type": "column"
              }
            ]
          ],
          "table": "air_quality",
          "timeColumn": "timestamp",
          "timeColumnType": "timestamp",
          "where": [
            {
              "name": "$__timeFilter",
              "params": [],
              "type": "macro"
            }
          ]
        },
        {
          "format": "time_series",
          "group": [],
          "hide": false,
          "metricColumn": "none",
          "rawQuery": true,
          "rawSql": "SELECT\n  UNIX_TIMESTAMP(timestamp) AS \"time\",\n  concentration\nFROM air_quality\nWHERE\n  $__timeFilter(timestamp) \n  AND node = 3\nORDER BY timestamp",
          "refId": "B",
          "select": [
            [
              {
                "params": [
                  "id"
                ],
                "type": "column"
              }
            ]
          ],
          "table": "air_quality",
          "timeColumn": "timestamp",
          "timeColumnType": "timestamp",
          "where": [
            {
              "name": "$__timeFilter",
              "params": [],
              "type": "macro"
            }
          ]
        }
      ],
      "timeFrom": null,
      "timeShift": null,
      "title": "Air Quality",
      "type": "timeseries"
    }
  ],
  "refresh": "",
  "schemaVersion": 27,
  "style": "dark",
  "tags": [],
  "templating": {
    "list": []
  },
  "time": {
    "from": "now-3h",
    "to": "now"
  },
  "timepicker": {},
  "timezone": "",
  "title": "SmartSauna",
  "uid": "orZcXV4nz",
  "version": 12
}
